{
  "generated_at": "2026-04-14",
  "macro_regime": "CALM",
  "composite_score": 4.0,
  "sesgo": "ALCISTA",
  "confianza": 62,
  "situacion": "R\u00e9gimen CALM, composite +4.0/30. 0 plays macro identificadas.",
  "narrativa": "El mercado se encuentra en r\u00e9gimen CALM con score +4.0. Contexto permite selecci\u00f3n VALUE disciplinada. Cerebro detecta 1 tickers a evitar y 1 potenciales short squeezes.",
  "acciones_inmediatas": [
    {
      "prioridad": 1,
      "accion": "VENDER",
      "instrumento": "BDL",
      "razon": "Quality decay HIGH: FCF yield cay\u00f3 2996.9pp (2998.0% \u2192 1.1%) | Caro vs peers en ",
      "catalizador": "Se\u00f1al AVOID activa en Cerebro",
      "size_hint": "grande (5%+)",
      "invalidacion": "Score Cerebro mejora a neutral"
    }
  ],
  "macro_plays": [],
  "macro_plays_commentary": "0 plays macro rule-based generadas sin IA.",
  "value_en_entorno": [],
  "value_en_entorno_razon": "Tickers VALUE seleccionados para r\u00e9gimen CALM.",
  "evitar": [
    {
      "ticker": "BDL",
      "razon": "Quality decay HIGH: FCF yield cay\u00f3 2996.9pp (2998.0% \u2192 1.1%) | Caro vs peers en "
    }
  ],
  "agenda_semana": [
    {
      "fecha": "2026-04-14",
      "evento": "Inicio Earnings Q1",
      "impacto": "MEDIO",
      "accion_sugerida": "Reducir riesgo antes / evaluar reacci\u00f3n del mercado despu\u00e9s"
    }
  ],
  "frase_del_dia": "No busques la aguja. Compra el pajar. \u2014 John Bogle",
  "mensaje_telegram": "\ud83e\udde0 CEREBRO 2026-04-14 | CALM (+4.0) | ALCISTA | VALUE:  | Evitar: BDL",
  "ai_powered": false
}