{
  "generated_at": "2026-04-14",
  "total": 39,
  "high_count": 10,
  "alerts": [
    {
      "ticker": "ABT",
      "type": "INSIDER_BUYING",
      "severity": "HIGH",
      "title": "Insider buying en ABT",
      "message": "6 compras por 2 directivos. Se\u00f1al de convicci\u00f3n interna.",
      "date": "2026-04-14",
      "data": {
        "purchase_count": 6.0,
        "unique_insiders": 2.0
      }
    },
    {
      "ticker": "JNJ",
      "type": "EARNINGS_WARNING",
      "severity": "HIGH",
      "title": "Earnings de JNJ en 0d",
      "message": "Score VALUE 52. Earnings en 0 d\u00edas \u2014 evita entrar.",
      "date": "2026-04-14",
      "data": {
        "days_to_earnings": 0.0,
        "value_score": 51.92
      }
    },
    {
      "ticker": "MSCI",
      "type": "INSIDER_BUYING",
      "severity": "HIGH",
      "title": "Insider buying en MSCI",
      "message": "4 compras por 2 directivos. Se\u00f1al de convicci\u00f3n interna.",
      "date": "2026-04-14",
      "data": {
        "purchase_count": 4.0,
        "unique_insiders": 2.0
      }
    },
    {
      "ticker": "NDAQ",
      "type": "INSIDER_BUYING",
      "severity": "HIGH",
      "title": "Insider buying en NDAQ",
      "message": "7 compras por 2 directivos. Se\u00f1al de convicci\u00f3n interna.",
      "date": "2026-04-14",
      "data": {
        "purchase_count": 7.0,
        "unique_insiders": 2.0
      }
    },
    {
      "ticker": "PEP",
      "type": "EARNINGS_WARNING",
      "severity": "HIGH",
      "title": "Earnings de PEP en 2d",
      "message": "Score VALUE 37. Earnings en 2 d\u00edas \u2014 evita entrar.",
      "date": "2026-04-14",
      "data": {
        "days_to_earnings": 2.0,
        "value_score": 37.2
      }
    },
    {
      "ticker": "PGR",
      "type": "EARNINGS_WARNING",
      "severity": "HIGH",
      "title": "Earnings de PGR en 1d",
      "message": "Score VALUE 47. Earnings en 1 d\u00edas \u2014 evita entrar.",
      "date": "2026-04-14",
      "data": {
        "days_to_earnings": 1.0,
        "value_score": 47.400000000000006
      }
    },
    {
      "ticker": "ROP",
      "type": "NEW_CONVERGENCE",
      "severity": "HIGH",
      "title": "Nueva convergencia: ROP",
      "message": "Aparece en 3 estrategias: VALUE, INSIDERS, MR. Score convergencia: 80.",
      "date": "2026-04-14",
      "data": {
        "strategies": [
          "VALUE",
          "INSIDERS",
          "MR"
        ],
        "convergence_score": 80
      }
    },
    {
      "ticker": "SPGI",
      "type": "INSIDER_BUYING",
      "severity": "HIGH",
      "title": "Insider buying en SPGI",
      "message": "7 compras por 2 directivos. Se\u00f1al de convicci\u00f3n interna.",
      "date": "2026-04-14",
      "data": {
        "purchase_count": 7.0,
        "unique_insiders": 2.0
      }
    },
    {
      "ticker": "TYL",
      "type": "INSIDER_BUYING",
      "severity": "HIGH",
      "title": "Insider buying en TYL",
      "message": "6 compras por 2 directivos. Se\u00f1al de convicci\u00f3n interna.",
      "date": "2026-04-14",
      "data": {
        "purchase_count": 6.0,
        "unique_insiders": 2.0
      }
    },
    {
      "ticker": "VRSK",
      "type": "NEW_CONVERGENCE",
      "severity": "HIGH",
      "title": "Nueva convergencia: VRSK",
      "message": "Aparece en 3 estrategias: VALUE, INSIDERS, OPTIONS. Score convergencia: 81.",
      "date": "2026-04-14",
      "data": {
        "strategies": [
          "VALUE",
          "INSIDERS",
          "OPTIONS"
        ],
        "convergence_score": 81
      }
    },
    {
      "ticker": "AON",
      "type": "INSIDER_BUYING",
      "severity": "MEDIUM",
      "title": "Insider buying en AON",
      "message": "3 compras por 1 directivos. Se\u00f1al de convicci\u00f3n interna.",
      "date": "2026-04-14",
      "data": {
        "purchase_count": 3.0,
        "unique_insiders": 1.0
      }
    },
    {
      "ticker": "AON",
      "type": "STREAK",
      "severity": "MEDIUM",
      "title": "AON \u2014 4 d\u00edas en convergencia",
      "message": "Lleva 4 d\u00edas consecutivos en 2 estrategias. Se\u00f1al persistente de alta convicci\u00f3n.",
      "date": "2026-04-14",
      "data": {
        "streak_days": 4,
        "strategies": [
          "VALUE",
          "INSIDERS"
        ]
      }
    },
    {
      "ticker": "APH",
      "type": "INSIDER_BUYING",
      "severity": "MEDIUM",
      "title": "Insider buying en APH",
      "message": "3 compras por 1 directivos. Se\u00f1al de convicci\u00f3n interna.",
      "date": "2026-04-14",
      "data": {
        "purchase_count": 3.0,
        "unique_insiders": 1.0
      }
    },
    {
      "ticker": "ASML.AS",
      "type": "EARNINGS_WARNING",
      "severity": "MEDIUM",
      "title": "Earnings de ASML.AS en 7d",
      "message": "Score VALUE 52. Earnings en 7 d\u00edas \u2014 evita entrar.",
      "date": "2026-04-14",
      "data": {
        "days_to_earnings": 7.0,
        "value_score": 51.5
      }
    },
    {
      "ticker": "CDNS",
      "type": "NEW_CONVERGENCE",
      "severity": "MEDIUM",
      "title": "Nueva convergencia: CDNS",
      "message": "Aparece en 2 estrategias: VALUE, INSIDERS. Score convergencia: 62.",
      "date": "2026-04-14",
      "data": {
        "strategies": [
          "VALUE",
          "INSIDERS"
        ],
        "convergence_score": 62
      }
    },
    {
      "ticker": "CME",
      "type": "NEW_CONVERGENCE",
      "severity": "MEDIUM",
      "title": "Nueva convergencia: CME",
      "message": "Aparece en 2 estrategias: VALUE, OPTIONS. Score convergencia: 48.",
      "date": "2026-04-14",
      "data": {
        "strategies": [
          "VALUE",
          "OPTIONS"
        ],
        "convergence_score": 48
      }
    },
    {
      "ticker": "CPRT",
      "type": "NEW_CONVERGENCE",
      "severity": "MEDIUM",
      "title": "Nueva convergencia: CPRT",
      "message": "Aparece en 2 estrategias: VALUE, OPTIONS. Score convergencia: 49.",
      "date": "2026-04-14",
      "data": {
        "strategies": [
          "VALUE",
          "OPTIONS"
        ],
        "convergence_score": 49
      }
    },
    {
      "ticker": "ECL",
      "type": "NEW_CONVERGENCE",
      "severity": "MEDIUM",
      "title": "Nueva convergencia: ECL",
      "message": "Aparece en 2 estrategias: VALUE, OPTIONS. Score convergencia: 49.",
      "date": "2026-04-14",
      "data": {
        "strategies": [
          "VALUE",
          "OPTIONS"
        ],
        "convergence_score": 49
      }
    },
    {
      "ticker": "EFX",
      "type": "INSIDER_BUYING",
      "severity": "MEDIUM",
      "title": "Insider buying en EFX",
      "message": "3 compras por 1 directivos. Se\u00f1al de convicci\u00f3n interna.",
      "date": "2026-04-14",
      "data": {
        "purchase_count": 3.0,
        "unique_insiders": 1.0
      }
    },
    {
      "ticker": "FAST",
      "type": "INSIDER_BUYING",
      "severity": "MEDIUM",
      "title": "Insider buying en FAST",
      "message": "7 compras por 1 directivos. Se\u00f1al de convicci\u00f3n interna.",
      "date": "2026-04-14",
      "data": {
        "purchase_count": 7.0,
        "unique_insiders": 1.0
      }
    },
    {
      "ticker": "HEI",
      "type": "NEW_CONVERGENCE",
      "severity": "MEDIUM",
      "title": "Nueva convergencia: HEI",
      "message": "Aparece en 2 estrategias: VALUE, INSIDERS. Score convergencia: 60.",
      "date": "2026-04-14",
      "data": {
        "strategies": [
          "VALUE",
          "INSIDERS"
        ],
        "convergence_score": 60
      }
    },
    {
      "ticker": "HOLN.SW",
      "type": "SCORE_DRIFT",
      "severity": "MEDIUM",
      "title": "Tesis en riesgo: HOLN.SW",
      "message": "Score baj\u00f3 20 pts (de 51 \u2192 31). Fundamentales pueden haber deteriorado \u2014 revisa la tesis.",
      "date": "2026-04-14",
      "data": {
        "original_score": 50.9,
        "current_score": 31.0,
        "drop": 19.9
      }
    },
    {
      "ticker": "IT",
      "type": "INSIDER_BUYING",
      "severity": "MEDIUM",
      "title": "Insider buying en IT",
      "message": "3 compras por 1 directivos. Se\u00f1al de convicci\u00f3n interna.",
      "date": "2026-04-14",
      "data": {
        "purchase_count": 3.0,
        "unique_insiders": 1.0
      }
    },
    {
      "ticker": "IT",
      "type": "NEW_CONVERGENCE",
      "severity": "MEDIUM",
      "title": "Nueva convergencia: IT",
      "message": "Aparece en 2 estrategias: VALUE, INSIDERS. Score convergencia: 61.",
      "date": "2026-04-14",
      "data": {
        "strategies": [
          "VALUE",
          "INSIDERS"
        ],
        "convergence_score": 61
      }
    },
    {
      "ticker": "ITW",
      "type": "SCORE_DRIFT",
      "severity": "MEDIUM",
      "title": "Tesis en riesgo: ITW",
      "message": "Score baj\u00f3 21 pts (de 61 \u2192 40). Fundamentales pueden haber deteriorado \u2014 revisa la tesis.",
      "date": "2026-04-14",
      "data": {
        "original_score": 61.2,
        "current_score": 39.9,
        "drop": 21.3
      }
    },
    {
      "ticker": "MSCI",
      "type": "EARNINGS_WARNING",
      "severity": "MEDIUM",
      "title": "Earnings de MSCI en 7d",
      "message": "Score VALUE 45. Earnings en 7 d\u00edas \u2014 evita entrar.",
      "date": "2026-04-14",
      "data": {
        "days_to_earnings": 7.0,
        "value_score": 44.68
      }
    },
    {
      "ticker": "MSCI",
      "type": "NEW_CONVERGENCE",
      "severity": "MEDIUM",
      "title": "Nueva convergencia: MSCI",
      "message": "Aparece en 2 estrategias: VALUE, INSIDERS. Score convergencia: 58.",
      "date": "2026-04-14",
      "data": {
        "strategies": [
          "VALUE",
          "INSIDERS"
        ],
        "convergence_score": 58
      }
    },
    {
      "ticker": "MSFT",
      "type": "INSIDER_BUYING",
      "severity": "MEDIUM",
      "title": "Insider buying en MSFT",
      "message": "3 compras por 1 directivos. Se\u00f1al de convicci\u00f3n interna.",
      "date": "2026-04-14",
      "data": {
        "purchase_count": 3.0,
        "unique_insiders": 1.0
      }
    },
    {
      "ticker": "MSFT",
      "type": "STREAK",
      "severity": "MEDIUM",
      "title": "MSFT \u2014 4 d\u00edas en convergencia",
      "message": "Lleva 4 d\u00edas consecutivos en 3 estrategias. Se\u00f1al persistente de alta convicci\u00f3n.",
      "date": "2026-04-14",
      "data": {
        "streak_days": 4,
        "strategies": [
          "VALUE",
          "INSIDERS",
          "OPTIONS"
        ]
      }
    },
    {
      "ticker": "NDAQ",
      "type": "NEW_CONVERGENCE",
      "severity": "MEDIUM",
      "title": "Nueva convergencia: NDAQ",
      "message": "Aparece en 2 estrategias: VALUE, INSIDERS. Score convergencia: 63.",
      "date": "2026-04-14",
      "data": {
        "strategies": [
          "VALUE",
          "INSIDERS"
        ],
        "convergence_score": 63
      }
    },
    {
      "ticker": "PAYX",
      "type": "INSIDER_BUYING",
      "severity": "MEDIUM",
      "title": "Insider buying en PAYX",
      "message": "4 compras por 1 directivos. Se\u00f1al de convicci\u00f3n interna.",
      "date": "2026-04-14",
      "data": {
        "purchase_count": 4.0,
        "unique_insiders": 1.0
      }
    },
    {
      "ticker": "PAYX",
      "type": "NEW_CONVERGENCE",
      "severity": "MEDIUM",
      "title": "Nueva convergencia: PAYX",
      "message": "Aparece en 2 estrategias: VALUE, INSIDERS. Score convergencia: 57.",
      "date": "2026-04-14",
      "data": {
        "strategies": [
          "VALUE",
          "INSIDERS"
        ],
        "convergence_score": 57
      }
    },
    {
      "ticker": "PG",
      "type": "NEW_CONVERGENCE",
      "severity": "MEDIUM",
      "title": "Nueva convergencia: PG",
      "message": "Aparece en 2 estrategias: VALUE, OPTIONS. Score convergencia: 50.",
      "date": "2026-04-14",
      "data": {
        "strategies": [
          "VALUE",
          "OPTIONS"
        ],
        "convergence_score": 50
      }
    },
    {
      "ticker": "ROP",
      "type": "MR_ZONE",
      "severity": "MEDIUM",
      "title": "ROP en zona oversold",
      "message": "RSI N/A, score MR 75. Calidad: \u2b50\u2b50 MUY BUENA. Posible rebote t\u00e9cnico.",
      "date": "2026-04-14",
      "data": {
        "reversion_score": 75.0,
        "rsi": null,
        "quality": "\u2b50\u2b50 MUY BUENA"
      }
    },
    {
      "ticker": "ROP",
      "type": "INSIDER_BUYING",
      "severity": "MEDIUM",
      "title": "Insider buying en ROP",
      "message": "3 compras por 1 directivos. Se\u00f1al de convicci\u00f3n interna.",
      "date": "2026-04-14",
      "data": {
        "purchase_count": 3.0,
        "unique_insiders": 1.0
      }
    },
    {
      "ticker": "SIE.DE",
      "type": "SCORE_DRIFT",
      "severity": "MEDIUM",
      "title": "Tesis en riesgo: SIE.DE",
      "message": "Score baj\u00f3 18 pts (de 51 \u2192 33). Fundamentales pueden haber deteriorado \u2014 revisa la tesis.",
      "date": "2026-04-14",
      "data": {
        "original_score": 51.4,
        "current_score": 33.4,
        "drop": 18.0
      }
    },
    {
      "ticker": "SPGI",
      "type": "STREAK",
      "severity": "MEDIUM",
      "title": "SPGI \u2014 4 d\u00edas en convergencia",
      "message": "Lleva 4 d\u00edas consecutivos en 2 estrategias. Se\u00f1al persistente de alta convicci\u00f3n.",
      "date": "2026-04-14",
      "data": {
        "streak_days": 4,
        "strategies": [
          "VALUE",
          "INSIDERS"
        ]
      }
    },
    {
      "ticker": "TYL",
      "type": "NEW_CONVERGENCE",
      "severity": "MEDIUM",
      "title": "Nueva convergencia: TYL",
      "message": "Aparece en 2 estrategias: VALUE, INSIDERS. Score convergencia: 56.",
      "date": "2026-04-14",
      "data": {
        "strategies": [
          "VALUE",
          "INSIDERS"
        ],
        "convergence_score": 56
      }
    },
    {
      "ticker": "VRSK",
      "type": "INSIDER_BUYING",
      "severity": "MEDIUM",
      "title": "Insider buying en VRSK",
      "message": "9 compras por 1 directivos. Se\u00f1al de convicci\u00f3n interna.",
      "date": "2026-04-14",
      "data": {
        "purchase_count": 9.0,
        "unique_insiders": 1.0
      }
    }
  ]
}